gravitools/__init__.py
gravitools/config.py
gravitools/corrections.py
gravitools/math.py
gravitools/outliers.py
gravitools/quantity.py
gravitools/report.py
gravitools/timeseries.py
gravitools/utils.py
gravitools/aqg/__init__.py
gravitools/aqg/__main__.py
gravitools/aqg/cli.py
gravitools/aqg/coriolis.py
gravitools/aqg/dashboard.py
gravitools/aqg/dataset.py
gravitools/aqg/files.py
gravitools/aqg/info.py
gravitools/aqg/rawdata.py
gravitools/aqg/report.py
gravitools/aqg/tilt.py
gravitools/aqg/utils.py
gravitools-0.2.0.dist-info/LICENSE.txt
gravitools-0.2.0.dist-info/METADATA
gravitools-0.2.0.dist-info/WHEEL
gravitools-0.2.0.dist-info/entry_points.txt
gravitools-0.2.0.dist-info/top_level.txt
gravitools-0.2.0.dist-info/RECORD
