Metadata-Version: 2.1
Name: gravitools
Version: 0.2.0
Summary: A collection of tools for gravimeter data analysis
Author-email: Marvin Reich <mreich@gfz-potsdam.de>, Julian Glässel <julian.glaessel@bkg.bund.de>
License:                       EUROPEAN UNION PUBLIC LICENCE v. 1.2
Project-URL: Repository, https://gitlab.opencode.de/bkg/gravitools
Project-URL: Documentation, https://gravitools.readthedocs.io/
Project-URL: Issues, https://gitlab.opencode.de/bkg/gravitools/-/issues
Project-URL: Changelog, https://gitlab.opencode.de/bkg/gravitools/-/blob/main/CHANGELOG.md
Keywords: gravimetry,gravimeter,geodesy
Classifier: Development Status :: 4 - Beta
Classifier: Intended Audience :: Science/Research
Classifier: License :: OSI Approved :: European Union Public Licence 1.2 (EUPL 1.2)
Classifier: Programming Language :: Python :: 3
Classifier: Programming Language :: Python :: 3.8
Classifier: Programming Language :: Python :: 3.9
Classifier: Programming Language :: Python :: 3.10
Classifier: Programming Language :: Python :: 3.11
Classifier: Programming Language :: Python :: 3.12
Classifier: Topic :: Scientific/Engineering :: Hydrology
Classifier: Topic :: Scientific/Engineering
Requires-Python: >=3.8
License-File: LICENSE.txt
Requires-Dist: allantools
Requires-Dist: fpdf2
Requires-Dist: matplotlib
Requires-Dist: netCDF4
Requires-Dist: numpy
Requires-Dist: packaging
Requires-Dist: pandas
Requires-Dist: pyyaml
Requires-Dist: requests
Requires-Dist: xarray
Provides-Extra: test
Requires-Dist: pytest; extra == "test"
Requires-Dist: pytest-cov; extra == "test"
Provides-Extra: docs
Requires-Dist: mkdocs; extra == "docs"
Requires-Dist: mkdocs-jupyter; extra == "docs"
Requires-Dist: mkdocs-material; extra == "docs"
Requires-Dist: mkdocstrings-python; extra == "docs"
Provides-Extra: dashboard
Requires-Dist: pyqtgraph; extra == "dashboard"
Requires-Dist: PySide6; extra == "dashboard"
Provides-Extra: all
Requires-Dist: pytest; extra == "all"
Requires-Dist: pytest-cov; extra == "all"
Requires-Dist: mkdocs; extra == "all"
Requires-Dist: mkdocs-jupyter; extra == "all"
Requires-Dist: mkdocs-material; extra == "all"
Requires-Dist: mkdocstrings-python; extra == "all"
Requires-Dist: pyqtgraph; extra == "all"
Requires-Dist: PySide6; extra == "all"
